weanalyze_altair_theme/__init__.py
weanalyze_altair_theme/theme.py
weanalyze_altair_theme/tokens.py
weanalyze_altair_theme/types.py
weanalyze_altair_theme-0.1.3.dist-info/LICENSE
weanalyze_altair_theme-0.1.3.dist-info/METADATA
weanalyze_altair_theme-0.1.3.dist-info/WHEEL
weanalyze_altair_theme-0.1.3.dist-info/entry_points.txt
weanalyze_altair_theme-0.1.3.dist-info/top_level.txt
weanalyze_altair_theme-0.1.3.dist-info/RECORD
