Metadata-Version: 2.1
Name: weanalyze-altair-theme
Version: 0.1.3
Summary: WeAnalyze's theme for Altair charts.
Home-page: https://github.com/weanalyze/weanalyze-altair-theme
Author: weanalyze
Project-URL: Bug Reports, https://github.com/weanalyze/weanalyze-altair-theme/issues
Project-URL: Source, https://github.com/weanalyze/weanalyze-altair-theme
Keywords: altair,theme,data,visualization
Classifier: Development Status :: 5 - Production/Stable
Classifier: Intended Audience :: Developers
Classifier: Intended Audience :: Information Technology
Classifier: Intended Audience :: Science/Research
Classifier: Natural Language :: English
Classifier: Operating System :: OS Independent
Classifier: Programming Language :: Python
Classifier: Programming Language :: Python :: 3
Classifier: Programming Language :: Python :: 3 :: Only
Classifier: Programming Language :: Python :: 3.7
Classifier: Programming Language :: Python :: 3.8
Classifier: Programming Language :: Python :: 3.9
Classifier: Programming Language :: Python :: 3.10
Classifier: Programming Language :: Python :: Implementation :: CPython
Classifier: Topic :: Scientific/Engineering :: Visualization
Classifier: Topic :: Utilities
Classifier: Typing :: Typed
Requires-Python: >=3.7, <4
License-File: LICENSE
Requires-Dist: altair (==4.*)
Requires-Dist: typing-extensions (==4.0.*)
